ukbcc/__init__.py
ukbcc/bulk.py
ukbcc/colors.py
ukbcc/filter.py
ukbcc/main.py
ukbcc/query.py
ukbcc/stats.py
ukbcc/ui.py
ukbcc/utils.py
ukbcc/webapp/__init__.py
ukbcc/webapp/app.py
ukbcc/webapp/webapp.py
ukbcc/webapp/apps/__init__.py
ukbcc/webapp/apps/config_app.py
ukbcc/webapp/apps/definitions_app.py
ukbcc/webapp/apps/include_kw_app.py
ukbcc/webapp/apps/kw_search_app.py
ukbcc/webapp/apps/query_app.py
ukbcc/webapp/apps/results_app.py
ukbcc-0.2.5.data/scripts/ukbcc
ukbcc-0.2.5.data/scripts/ukbcc_cli
ukbcc-0.2.5.dist-info/LICENSE.md
ukbcc-0.2.5.dist-info/METADATA
ukbcc-0.2.5.dist-info/WHEEL
ukbcc-0.2.5.dist-info/top_level.txt
ukbcc-0.2.5.dist-info/RECORD
