Metadata-Version: 2.1
Name: ukbcc
Version: 0.2.5
Summary: Tool to define a UKBB cohort
Home-page: https://github.com/tool-bin/ukbcc/
Author: Isabell Kiral, Nathalie Willems, Benjamin Goudey
Author-email: isa.kiral@gmail.com
License: APACHE 2
Download-URL: https://github.com/tool-bin/ukbcc/tarball/0.2.5
Platform: UNKNOWN
Classifier: Development Status :: 3 - Alpha
Classifier: Intended Audience :: Developers
Classifier: Natural Language :: English
Classifier: Intended Audience :: Science/Research
Requires-Python: >=3.6
Requires-Dist: sphinx (>=3.0.3)
Requires-Dist: sphinx-rtd-theme (>=0.4.3)
Requires-Dist: nose (>=1.3.7)
Requires-Dist: coverage (>=5.1)
Requires-Dist: pypi-publisher (>=0.0.4)
Requires-Dist: pandas (>=1.0.3)
Requires-Dist: requests (>=2.23.0)
Requires-Dist: numpy (>=1.18)
Requires-Dist: dash (>=1.13.4)
Requires-Dist: dash-bootstrap-components (>=0.10.3)
Requires-Dist: pytest (>=6.0.0)
